main/__init__.py
main/__main__.py
main/config.json
main/server.py
main/voice-types.json
mcp_bytedance_tts-1.0.13.dist-info/METADATA
mcp_bytedance_tts-1.0.13.dist-info/WHEEL
mcp_bytedance_tts-1.0.13.dist-info/entry_points.txt
mcp_bytedance_tts-1.0.13.dist-info/licenses/LICENSE
mcp_bytedance_tts-1.0.13.dist-info/RECORD
