Metadata-Version: 2.4
Name: mcp-bytedance-tts
Version: 1.0.13
Summary: MCP server for text-to-speech using bytedance-tts - generates audio from text
Project-URL: Homepage, https://github.com/aardpro/mcp-bytedance-tts
Project-URL: Repository, https://github.com/aardpro/mcp-bytedance-tts
Project-URL: Issues, https://github.com/aardpro/mcp-bytedance-tts/issues
Author-email: aardpro <chileehong@outlook.com>
License-Expression: MIT
License-File: LICENSE
Keywords: audio,bytedance-tts,mcp,text-to-speech,tts
Classifier: Development Status :: 4 - Beta
Classifier: Intended Audience :: Developers
Classifier: License :: OSI Approved :: MIT License
Classifier: Programming Language :: Python :: 3
Classifier: Programming Language :: Python :: 3.10
Classifier: Programming Language :: Python :: 3.11
Classifier: Programming Language :: Python :: 3.12
Requires-Python: >=3.10
Requires-Dist: mcp>=1.0.0
Requires-Dist: minio>=7.2.0
Requires-Dist: requests
Provides-Extra: dev
Requires-Dist: pytest>=7.0.0; extra == 'dev'
Requires-Dist: ruff>=0.1.0; extra == 'dev'
